<annotation verified="no">
  <folder>JPEGImages</folder>
  <filename>000131</filename>
  <path>F:\A-zk\Rotating target\JPEGImages\000131.jpg</path>
  <source>
    <database>Unknown</database>
  </source>
  <size>
    <width>2400</width>
    <height>1600</height>
    <depth>3</depth>
  </size>
  <segmented>0</segmented>
  <object>
    <type>robndbox</type>
    <name>defective_insulator</name>
    <pose>Unspecified</pose>
    <truncated>0</truncated>
    <difficult>0</difficult>
    <robndbox>
      <cx>2070.5595</cx>
      <cy>598.8179</cy>
      <w>652.4649</w>
      <h>402.0199</h>
      <angle>0.01</angle>
    </robndbox>
  </object>
  <object>
    <type>robndbox</type>
    <name>broken_defect</name>
    <pose>Unspecified</pose>
    <truncated>0</truncated>
    <difficult>0</difficult>
    <robndbox>
      <cx>1840.8333</cx>
      <cy>643.0556</cy>
      <w>189.0</w>
      <h>333.0</h>
      <angle>0.0</angle>
    </robndbox>
  </object>
  <object>
    <type>robndbox</type>
    <name>good_insulator</name>
    <pose>Unspecified</pose>
    <truncated>0</truncated>
    <difficult>0</difficult>
    <robndbox>
      <cx>900.4642</cx>
      <cy>247.2778</cy>
      <w>741.7382</w>
      <h>494.5556</h>
      <angle>0.0</angle>
    </robndbox>
  </object>
</annotation>
