<annotation verified="no">
  <folder>JPEGImages</folder>
  <filename>000581</filename>
  <path>F:\A-zk\Rotating target\JPEGImages\000581.jpg</path>
  <source>
    <database>Unknown</database>
  </source>
  <size>
    <width>1152</width>
    <height>864</height>
    <depth>3</depth>
  </size>
  <segmented>0</segmented>
  <object>
    <type>robndbox</type>
    <name>good_insulator</name>
    <pose>Unspecified</pose>
    <truncated>0</truncated>
    <difficult>0</difficult>
    <robndbox>
      <cx>559.4573</cx>
      <cy>425.8684</cy>
      <w>812.9</w>
      <h>44.5213</h>
      <angle>0.23</angle>
    </robndbox>
  </object>
  <object>
    <type>robndbox</type>
    <name>good_insulator</name>
    <pose>Unspecified</pose>
    <truncated>0</truncated>
    <difficult>0</difficult>
    <robndbox>
      <cx>577.8455</cx>
      <cy>387.4766</cy>
      <w>786.1637</w>
      <h>42.901</h>
      <angle>0.24</angle>
    </robndbox>
  </object>
  <object>
    <type>robndbox</type>
    <name>good_insulator</name>
    <pose>Unspecified</pose>
    <truncated>0</truncated>
    <difficult>0</difficult>
    <robndbox>
      <cx>972.2276</cx>
      <cy>156.5637</cy>
      <w>297.1596</w>
      <h>30.4105</h>
      <angle>0.18</angle>
    </robndbox>
  </object>
</annotation>
