<annotation verified="no">
  <folder>JPEGImages</folder>
  <filename>000489</filename>
  <path>F:\A-zk\Rotating target\JPEGImages\000489.jpg</path>
  <source>
    <database>Unknown</database>
  </source>
  <size>
    <width>1286</width>
    <height>854</height>
    <depth>3</depth>
  </size>
  <segmented>0</segmented>
  <object>
    <type>robndbox</type>
    <name>defective_insulator</name>
    <pose>Unspecified</pose>
    <truncated>0</truncated>
    <difficult>0</difficult>
    <robndbox>
      <cx>760.9005</cx>
      <cy>626.0611</cy>
      <w>205.1683</w>
      <h>442.6438</h>
      <angle>3.081593</angle>
    </robndbox>
  </object>
  <object>
    <type>robndbox</type>
    <name>flashover_defect</name>
    <pose>Unspecified</pose>
    <truncated>0</truncated>
    <difficult>0</difficult>
    <robndbox>
      <cx>750.998</cx>
      <cy>456.5747</cy>
      <w>202.6063</w>
      <h>99.5557</h>
      <angle>3.071593</angle>
    </robndbox>
  </object>
</annotation>
