<annotation verified="no">
  <folder>JPEGImages</folder>
  <filename>000780</filename>
  <path>F:\A-zk\Rotating target\JPEGImages\000780.jpg</path>
  <source>
    <database>Unknown</database>
  </source>
  <size>
    <width>1152</width>
    <height>864</height>
    <depth>3</depth>
  </size>
  <segmented>0</segmented>
  <object>
    <type>robndbox</type>
    <name>good_insulator</name>
    <pose>Unspecified</pose>
    <truncated>0</truncated>
    <difficult>0</difficult>
    <robndbox>
      <cx>675.2257</cx>
      <cy>450.4379</cy>
      <w>504.0237</w>
      <h>31.1342</h>
      <angle>3.011593</angle>
    </robndbox>
  </object>
  <object>
    <type>robndbox</type>
    <name>good_insulator</name>
    <pose>Unspecified</pose>
    <truncated>0</truncated>
    <difficult>0</difficult>
    <robndbox>
      <cx>684.0981</cx>
      <cy>482.4196</cy>
      <w>518.2217</w>
      <h>36.4732</h>
      <angle>3.001593</angle>
    </robndbox>
  </object>
</annotation>
