<annotation verified="no">
  <folder>JPEGImages</folder>
  <filename>000817</filename>
  <path>F:\A-zk\Rotating target\JPEGImages\000817.jpg</path>
  <source>
    <database>Unknown</database>
  </source>
  <size>
    <width>1152</width>
    <height>864</height>
    <depth>3</depth>
  </size>
  <segmented>0</segmented>
  <object>
    <type>robndbox</type>
    <name>good_insulator</name>
    <pose>Unspecified</pose>
    <truncated>0</truncated>
    <difficult>0</difficult>
    <robndbox>
      <cx>447.629</cx>
      <cy>631.2043</cy>
      <w>575.0</w>
      <h>68.0</h>
      <angle>3.131593</angle>
    </robndbox>
  </object>
  <object>
    <type>robndbox</type>
    <name>good_insulator</name>
    <pose>Unspecified</pose>
    <truncated>0</truncated>
    <difficult>0</difficult>
    <robndbox>
      <cx>284.129</cx>
      <cy>473.7043</cy>
      <w>240.0</w>
      <h>31.0</h>
      <angle>3.111593</angle>
    </robndbox>
  </object>
  <object>
    <type>robndbox</type>
    <name>good_insulator</name>
    <pose>Unspecified</pose>
    <truncated>0</truncated>
    <difficult>0</difficult>
    <robndbox>
      <cx>248.129</cx>
      <cy>24.7043</cy>
      <w>262.0</w>
      <h>31.0</h>
      <angle>0.0</angle>
    </robndbox>
  </object>
  <object>
    <type>robndbox</type>
    <name>good_insulator</name>
    <pose>Unspecified</pose>
    <truncated>0</truncated>
    <difficult>0</difficult>
    <robndbox>
      <cx>1104.2545</cx>
      <cy>737.3462</cy>
      <w>33.2397</w>
      <h>250.3673</h>
      <angle>0.11</angle>
    </robndbox>
  </object>
  <object>
    <type>robndbox</type>
    <name>broken_defect</name>
    <pose>Unspecified</pose>
    <truncated>0</truncated>
    <difficult>0</difficult>
    <robndbox>
      <cx>1110.6781</cx>
      <cy>689.4193</cy>
      <w>33.1007</w>
      <h>16.9105</h>
      <angle>0.13</angle>
    </robndbox>
  </object>
</annotation>
