{"box_data": [{"position": {"minX": 361.628662109375, "minY": 185.39840698242188, "maxX": 564.871337890625, "maxY": 308.8515930175781}, "class_id": 0, "box_caption": "defective_insulator 0.067", "scores": {"class_score": 0.06719970703125}, "domain": "pixel"}, {"position": {"minX": 330.457275390625, "minY": 169.82388305664062, "maxX": 533.542724609375, "maxY": 312.1761169433594}, "class_id": 0, "box_caption": "defective_insulator 0.065", "scores": {"class_score": 0.064697265625}, "domain": "pixel"}, {"position": {"minX": 398.2009582519531, "minY": 199.87451171875, "maxX": 449.7990417480469, "maxY": 269.62548828125}, "class_id": 3, "box_caption": "flashover_defect 0.043", "scores": {"class_score": 0.04290771484375}, "domain": "pixel"}, {"position": {"minX": 381.9888916015625, "minY": 111.50592041015625, "maxX": 543.5111083984375, "maxY": 382.49407958984375}, "class_id": 0, "box_caption": "defective_insulator 0.042", "scores": {"class_score": 0.042236328125}, "domain": "pixel"}, {"position": {"minX": 396.68133544921875, "minY": 179.5113525390625, "maxX": 591.3186645507812, "maxY": 335.4886474609375}, "class_id": 0, "box_caption": "defective_insulator 0.040", "scores": {"class_score": 0.0399169921875}, "domain": "pixel"}, {"position": {"minX": 391.5816650390625, "minY": 113.67343139648438, "maxX": 596.9183349609375, "maxY": 385.3265686035156}, "class_id": 0, "box_caption": "defective_insulator 0.038", "scores": {"class_score": 0.038299560546875}, "domain": "pixel"}, {"position": {"minX": 333.3736572265625, "minY": 108.38125610351562, "maxX": 531.1263427734375, "maxY": 374.6187438964844}, "class_id": 0, "box_caption": "defective_insulator 0.038", "scores": {"class_score": 0.03826904296875}, "domain": "pixel"}, {"position": {"minX": 384.58709716796875, "minY": 170.63040161132812, "maxX": 481.41290283203125, "maxY": 311.8695983886719}, "class_id": 0, "box_caption": "defective_insulator 0.037", "scores": {"class_score": 0.036773681640625}, "domain": "pixel"}, {"position": {"minX": 397.4344177246094, "minY": 202.34426879882812, "maxX": 482.0655822753906, "maxY": 284.4057312011719}, "class_id": 3, "box_caption": "flashover_defect 0.035", "scores": {"class_score": 0.034942626953125}, "domain": "pixel"}, {"position": {"minX": 384.3358459472656, "minY": 201.33853149414062, "maxX": 433.1641540527344, "maxY": 266.4114685058594}, "class_id": 3, "box_caption": "flashover_defect 0.032", "scores": {"class_score": 0.032012939453125}, "domain": "pixel"}, {"position": {"minX": 385.20416259765625, "minY": 199.17861938476562, "maxX": 542.7958374023438, "maxY": 294.5713806152344}, "class_id": 3, "box_caption": "flashover_defect 0.030", "scores": {"class_score": 0.0298004150390625}, "domain": "pixel"}, {"position": {"minX": 418.52398681640625, "minY": 199.16836547851562, "maxX": 491.97601318359375, "maxY": 296.0816345214844}, "class_id": 3, "box_caption": "flashover_defect 0.029", "scores": {"class_score": 0.0290679931640625}, "domain": "pixel"}, {"position": {"minX": 113.82168579101562, "minY": 133.81265258789062, "maxX": 303.4283142089844, "maxY": 470.6873474121094}, "class_id": 0, "box_caption": "defective_insulator 0.028", "scores": {"class_score": 0.02813720703125}, "domain": "pixel"}, {"position": {"minX": 384.58709716796875, "minY": 170.63040161132812, "maxX": 481.41290283203125, "maxY": 311.8695983886719}, "class_id": 3, "box_caption": "flashover_defect 0.028", "scores": {"class_score": 0.0277557373046875}, "domain": "pixel"}, {"position": {"minX": 460.84918212890625, "minY": 204.31927490234375, "maxX": 545.1508178710938, "maxY": 286.18072509765625}, "class_id": 3, "box_caption": "flashover_defect 0.027", "scores": {"class_score": 0.0267333984375}, "domain": "pixel"}, {"position": {"minX": 448.90423583984375, "minY": 196.41986083984375, "maxX": 527.0957641601562, "maxY": 299.08013916015625}, "class_id": 3, "box_caption": "flashover_defect 0.026", "scores": {"class_score": 0.0256500244140625}, "domain": "pixel"}, {"position": {"minX": 308.8114013671875, "minY": 138.3385009765625, "maxX": 506.6885986328125, "maxY": 328.1614990234375}, "class_id": 0, "box_caption": "defective_insulator 0.024", "scores": {"class_score": 0.02447509765625}, "domain": "pixel"}, {"position": {"minX": 141.709716796875, "minY": 200.17681884765625, "maxX": 339.040283203125, "maxY": 401.32318115234375}, "class_id": 0, "box_caption": "defective_insulator 0.023", "scores": {"class_score": 0.022735595703125}, "domain": "pixel"}, {"position": {"minX": 398.2009582519531, "minY": 199.87451171875, "maxX": 449.7990417480469, "maxY": 269.62548828125}, "class_id": 1, "box_caption": "broken_defect 0.022", "scores": {"class_score": 0.022003173828125}, "domain": "pixel"}, {"position": {"minX": 398.2009582519531, "minY": 199.87451171875, "maxX": 449.7990417480469, "maxY": 269.62548828125}, "class_id": 0, "box_caption": "defective_insulator 0.022", "scores": {"class_score": 0.0218505859375}, "domain": "pixel"}, {"position": {"minX": 397.4344177246094, "minY": 202.34426879882812, "maxX": 482.0655822753906, "maxY": 284.4057312011719}, "class_id": 0, "box_caption": "defective_insulator 0.019", "scores": {"class_score": 0.019073486328125}, "domain": "pixel"}, {"position": {"minX": 397.4344177246094, "minY": 202.34426879882812, "maxX": 482.0655822753906, "maxY": 284.4057312011719}, "class_id": 1, "box_caption": "broken_defect 0.019", "scores": {"class_score": 0.018585205078125}, "domain": "pixel"}, {"position": {"minX": 368.32025146484375, "minY": 201.88796997070312, "maxX": 416.67974853515625, "maxY": 267.1120300292969}, "class_id": 3, "box_caption": "flashover_defect 0.017", "scores": {"class_score": 0.0171966552734375}, "domain": "pixel"}, {"position": {"minX": 385.20416259765625, "minY": 199.17861938476562, "maxX": 542.7958374023438, "maxY": 294.5713806152344}, "class_id": 1, "box_caption": "broken_defect 0.017", "scores": {"class_score": 0.0171356201171875}, "domain": "pixel"}, {"position": {"minX": 418.52398681640625, "minY": 199.16836547851562, "maxX": 491.97601318359375, "maxY": 296.0816345214844}, "class_id": 1, "box_caption": "broken_defect 0.017", "scores": {"class_score": 0.0168609619140625}, "domain": "pixel"}, {"position": {"minX": 384.3358459472656, "minY": 201.33853149414062, "maxX": 433.1641540527344, "maxY": 266.4114685058594}, "class_id": 1, "box_caption": "broken_defect 0.017", "scores": {"class_score": 0.0168304443359375}, "domain": "pixel"}, {"position": {"minX": 135.79891967773438, "minY": 205.07275390625, "maxX": 287.7010803222656, "maxY": 404.42724609375}, "class_id": 0, "box_caption": "defective_insulator 0.017", "scores": {"class_score": 0.016815185546875}, "domain": "pixel"}, {"position": {"minX": 232.32952880859375, "minY": -18.928611755371094, "maxX": 434.17047119140625, "maxY": 115.2411117553711}, "class_id": 0, "box_caption": "defective_insulator 0.017", "scores": {"class_score": 0.016754150390625}, "domain": "pixel"}, {"position": {"minX": 384.3358459472656, "minY": 201.33853149414062, "maxX": 433.1641540527344, "maxY": 266.4114685058594}, "class_id": 0, "box_caption": "defective_insulator 0.016", "scores": {"class_score": 0.016448974609375}, "domain": "pixel"}, {"position": {"minX": 454.14453125, "minY": 206.4566650390625, "maxX": 521.85546875, "maxY": 272.7933349609375}, "class_id": 3, "box_caption": "flashover_defect 0.016", "scores": {"class_score": 0.0160980224609375}, "domain": "pixel"}, {"position": {"minX": 388.8524169921875, "minY": -15.920829772949219, "maxX": 601.6475830078125, "maxY": 107.29582977294922}, "class_id": 2, "box_caption": "good_insulator 0.016", "scores": {"class_score": 0.015869140625}, "domain": "pixel"}, {"position": {"minX": 448.90423583984375, "minY": 196.41986083984375, "maxX": 527.0957641601562, "maxY": 299.08013916015625}, "class_id": 1, "box_caption": "broken_defect 0.016", "scores": {"class_score": 0.015838623046875}, "domain": "pixel"}, {"position": {"minX": 460.84918212890625, "minY": 204.31927490234375, "maxX": 545.1508178710938, "maxY": 286.18072509765625}, "class_id": 1, "box_caption": "broken_defect 0.016", "scores": {"class_score": 0.015777587890625}, "domain": "pixel"}, {"position": {"minX": 418.52398681640625, "minY": 199.16836547851562, "maxX": 491.97601318359375, "maxY": 296.0816345214844}, "class_id": 0, "box_caption": "defective_insulator 0.016", "scores": {"class_score": 0.0157318115234375}, "domain": "pixel"}, {"position": {"minX": 446.30029296875, "minY": -93.12165832519531, "maxX": 560.19970703125, "maxY": 174.8716583251953}, "class_id": 0, "box_caption": "defective_insulator 0.016", "scores": {"class_score": 0.0156707763671875}, "domain": "pixel"}, {"position": {"minX": 388.8524169921875, "minY": -15.920829772949219, "maxX": 601.6475830078125, "maxY": 107.29582977294922}, "class_id": 0, "box_caption": "defective_insulator 0.015", "scores": {"class_score": 0.01546478271484375}, "domain": "pixel"}, {"position": {"minX": 305.5534973144531, "minY": 14.360649108886719, "maxX": 348.4465026855469, "maxY": 73.76435089111328}, "class_id": 3, "box_caption": "flashover_defect 0.015", "scores": {"class_score": 0.01515960693359375}, "domain": "pixel"}, {"position": {"minX": 384.58709716796875, "minY": 170.63040161132812, "maxX": 481.41290283203125, "maxY": 311.8695983886719}, "class_id": 1, "box_caption": "broken_defect 0.015", "scores": {"class_score": 0.0151519775390625}, "domain": "pixel"}, {"position": {"minX": 448.90423583984375, "minY": 196.41986083984375, "maxX": 527.0957641601562, "maxY": 299.08013916015625}, "class_id": 0, "box_caption": "defective_insulator 0.015", "scores": {"class_score": 0.014984130859375}, "domain": "pixel"}, {"position": {"minX": 333.6708679199219, "minY": 198.77114868164062, "maxX": 472.3291320800781, "maxY": 279.9788513183594}, "class_id": 3, "box_caption": "flashover_defect 0.015", "scores": {"class_score": 0.0149383544921875}, "domain": "pixel"}, {"position": {"minX": 267.13287353515625, "minY": -89.73969268798828, "maxX": 388.36712646484375, "maxY": 177.48968505859375}, "class_id": 0, "box_caption": "defective_insulator 0.015", "scores": {"class_score": 0.01476287841796875}, "domain": "pixel"}, {"position": {"minX": 398.1210021972656, "minY": 200.68292236328125, "maxX": 457.3789978027344, "maxY": 256.81707763671875}, "class_id": 3, "box_caption": "flashover_defect 0.015", "scores": {"class_score": 0.01470947265625}, "domain": "pixel"}, {"position": {"minX": 460.84918212890625, "minY": 204.31927490234375, "maxX": 545.1508178710938, "maxY": 286.18072509765625}, "class_id": 0, "box_caption": "defective_insulator 0.014", "scores": {"class_score": 0.01436614990234375}, "domain": "pixel"}, {"position": {"minX": 313.00860595703125, "minY": 172.68310546875, "maxX": 547.9913940429688, "maxY": 291.06689453125}, "class_id": 0, "box_caption": "defective_insulator 0.014", "scores": {"class_score": 0.01390838623046875}, "domain": "pixel"}, {"position": {"minX": 135.79891967773438, "minY": 205.07275390625, "maxX": 287.7010803222656, "maxY": 404.42724609375}, "class_id": 3, "box_caption": "flashover_defect 0.013", "scores": {"class_score": 0.01309967041015625}, "domain": "pixel"}, {"position": {"minX": 483.15643310546875, "minY": 10.361274719238281, "maxX": 523.8435668945312, "maxY": 70.38872528076172}, "class_id": 3, "box_caption": "flashover_defect 0.013", "scores": {"class_score": 0.01305389404296875}, "domain": "pixel"}, {"position": {"minX": 289.007080078125, "minY": 15.806608200073242, "maxX": 336.492919921875, "maxY": 74.44338989257812}, "class_id": 3, "box_caption": "flashover_defect 0.013", "scores": {"class_score": 0.01302337646484375}, "domain": "pixel"}, {"position": {"minX": 178.3332061767578, "minY": 15.126144409179688, "maxX": 446.66680908203125, "maxY": 74.43635559082031}, "class_id": 0, "box_caption": "defective_insulator 0.013", "scores": {"class_score": 0.01264190673828125}, "domain": "pixel"}, {"position": {"minX": 174.91229248046875, "minY": 204.76968383789062, "maxX": 308.08770751953125, "maxY": 400.2303161621094}, "class_id": 3, "box_caption": "flashover_defect 0.013", "scores": {"class_score": 0.01259613037109375}, "domain": "pixel"}, {"position": {"minX": 475.12200927734375, "minY": 204.2239990234375, "maxX": 524.8779907226562, "maxY": 267.7760009765625}, "class_id": 3, "box_caption": "flashover_defect 0.013", "scores": {"class_score": 0.012542724609375}, "domain": "pixel"}, {"position": {"minX": 76.00042724609375, "minY": 247.3375244140625, "maxX": 281.74957275390625, "maxY": 396.1624755859375}, "class_id": 0, "box_caption": "defective_insulator 0.012", "scores": {"class_score": 0.01187896728515625}, "domain": "pixel"}, {"position": {"minX": 403.3426513671875, "minY": 169.21435546875, "maxX": 604.1573486328125, "maxY": 322.28564453125}, "class_id": 3, "box_caption": "flashover_defect 0.012", "scores": {"class_score": 0.011749267578125}, "domain": "pixel"}, {"position": {"minX": 418.8405456542969, "minY": 228.48526000976562, "maxX": 485.1594543457031, "maxY": 291.5147399902344}, "class_id": 3, "box_caption": "flashover_defect 0.012", "scores": {"class_score": 0.01160430908203125}, "domain": "pixel"}, {"position": {"minX": 155.10284423828125, "minY": 287.92156982421875, "maxX": 213.64715576171875, "maxY": 363.57843017578125}, "class_id": 3, "box_caption": "flashover_defect 0.012", "scores": {"class_score": 0.01153564453125}, "domain": "pixel"}, {"position": {"minX": 493.6954345703125, "minY": 205.0877685546875, "maxX": 542.3045654296875, "maxY": 271.4122314453125}, "class_id": 3, "box_caption": "flashover_defect 0.012", "scores": {"class_score": 0.01153564453125}, "domain": "pixel"}, {"position": {"minX": 396.46014404296875, "minY": -61.228759765625, "maxX": 611.5398559570312, "maxY": 143.103759765625}, "class_id": 0, "box_caption": "defective_insulator 0.012", "scores": {"class_score": 0.011505126953125}, "domain": "pixel"}, {"position": {"minX": 179.9566192626953, "minY": 45.818328857421875, "maxX": 364.54339599609375, "maxY": 356.1816711425781}, "class_id": 0, "box_caption": "defective_insulator 0.011", "scores": {"class_score": 0.01126861572265625}, "domain": "pixel"}, {"position": {"minX": 231.28863525390625, "minY": 132.74778747558594, "maxX": 321.71136474609375, "maxY": 210.00221252441406}, "class_id": 3, "box_caption": "flashover_defect 0.011", "scores": {"class_score": 0.01125335693359375}, "domain": "pixel"}, {"position": {"minX": 175.1055908203125, "minY": 107.014404296875, "maxX": 374.8944091796875, "maxY": 255.985595703125}, "class_id": 0, "box_caption": "defective_insulator 0.011", "scores": {"class_score": 0.01105499267578125}, "domain": "pixel"}, {"position": {"minX": 447.394287109375, "minY": -74.5272216796875, "maxX": 539.105712890625, "maxY": 159.1522216796875}, "class_id": 2, "box_caption": "good_insulator 0.011", "scores": {"class_score": 0.0110015869140625}, "domain": "pixel"}, {"position": {"minX": 308.8114013671875, "minY": 138.3385009765625, "maxX": 506.6885986328125, "maxY": 328.1614990234375}, "class_id": 3, "box_caption": "flashover_defect 0.011", "scores": {"class_score": 0.01094818115234375}, "domain": "pixel"}, {"position": {"minX": 446.30029296875, "minY": -93.12165832519531, "maxX": 560.19970703125, "maxY": 174.8716583251953}, "class_id": 2, "box_caption": "good_insulator 0.011", "scores": {"class_score": 0.010894775390625}, "domain": "pixel"}, {"position": {"minX": 330.02899169921875, "minY": -51.61134338378906, "maxX": 535.4710083007812, "maxY": 130.11134338378906}, "class_id": 0, "box_caption": "defective_insulator 0.011", "scores": {"class_score": 0.01088714599609375}, "domain": "pixel"}, {"position": {"minX": 343.78265380859375, "minY": -55.30036926269531, "maxX": 567.7173461914062, "maxY": 134.9253692626953}, "class_id": 2, "box_caption": "good_insulator 0.011", "scores": {"class_score": 0.0108642578125}, "domain": "pixel"}, {"position": {"minX": 417.6996154785156, "minY": 218.48333740234375, "maxX": 470.3003845214844, "maxY": 285.26666259765625}, "class_id": 3, "box_caption": "flashover_defect 0.011", "scores": {"class_score": 0.010711669921875}, "domain": "pixel"}, {"position": {"minX": 447.394287109375, "minY": -74.5272216796875, "maxX": 539.105712890625, "maxY": 159.1522216796875}, "class_id": 0, "box_caption": "defective_insulator 0.011", "scores": {"class_score": 0.01056671142578125}, "domain": "pixel"}, {"position": {"minX": 426.394287109375, "minY": 168.33349609375, "maxX": 611.605712890625, "maxY": 321.41650390625}, "class_id": 0, "box_caption": "defective_insulator 0.011", "scores": {"class_score": 0.01055908203125}, "domain": "pixel"}, {"position": {"minX": 396.46014404296875, "minY": -61.228759765625, "maxX": 611.5398559570312, "maxY": 143.103759765625}, "class_id": 2, "box_caption": "good_insulator 0.010", "scores": {"class_score": 0.010467529296875}, "domain": "pixel"}, {"position": {"minX": 398.1210021972656, "minY": 200.68292236328125, "maxX": 457.3789978027344, "maxY": 256.81707763671875}, "class_id": 1, "box_caption": "broken_defect 0.010", "scores": {"class_score": 0.01043701171875}, "domain": "pixel"}, {"position": {"minX": -0.12406158447265625, "minY": 80.65621948242188, "maxX": 109.06156158447266, "maxY": 281.3437805175781}, "class_id": 0, "box_caption": "defective_insulator 0.010", "scores": {"class_score": 0.01031494140625}, "domain": "pixel"}, {"position": {"minX": 438.9470520019531, "minY": 229.03762817382812, "maxX": 504.5529479980469, "maxY": 315.9623718261719}, "class_id": 3, "box_caption": "flashover_defect 0.010", "scores": {"class_score": 0.01026153564453125}, "domain": "pixel"}, {"position": {"minX": 461.5640869140625, "minY": -81.39663696289062, "maxX": 577.4359130859375, "maxY": 163.52163696289062}, "class_id": 2, "box_caption": "good_insulator 0.010", "scores": {"class_score": 0.01021575927734375}, "domain": "pixel"}, {"position": {"minX": 433.5233154296875, "minY": 202.82611083984375, "maxX": 509.4766845703125, "maxY": 277.17388916015625}, "class_id": 3, "box_caption": "flashover_defect 0.010", "scores": {"class_score": 0.0100555419921875}, "domain": "pixel"}], "class_labels": {"0": "defective_insulator", "1": "broken_defect", "2": "good_insulator", "3": "flashover_defect"}}