{"box_data": [{"position": {"minX": 63.07453918457031, "minY": -142.22711181640625, "maxX": 486.92547607421875, "maxY": 554.9771728515625}, "class_id": 0, "box_caption": "defective_insulator 0.260", "scores": {"class_score": 0.260009765625}, "domain": "pixel"}, {"position": {"minX": 175.55825805664062, "minY": 44.012725830078125, "maxX": 391.4417419433594, "maxY": 380.7373046875}, "class_id": 0, "box_caption": "defective_insulator 0.252", "scores": {"class_score": 0.251708984375}, "domain": "pixel"}, {"position": {"minX": 286.21551513671875, "minY": 279.3189392089844, "maxX": 407.78448486328125, "maxY": 370.1810607910156}, "class_id": 3, "box_caption": "flashover_defect 0.121", "scores": {"class_score": 0.12115478515625}, "domain": "pixel"}, {"position": {"minX": 100.02188110351562, "minY": 94.6527099609375, "maxX": 494.4781188964844, "maxY": 370.3472900390625}, "class_id": 0, "box_caption": "defective_insulator 0.108", "scores": {"class_score": 0.10809326171875}, "domain": "pixel"}, {"position": {"minX": 155.43521118164062, "minY": 23.888946533203125, "maxX": 355.0647888183594, "maxY": 326.61102294921875}, "class_id": 1, "box_caption": "broken_defect 0.094", "scores": {"class_score": 0.093505859375}, "domain": "pixel"}, {"position": {"minX": 211.02346801757812, "minY": -28.379791259765625, "maxX": 332.4765319824219, "maxY": 418.37982177734375}, "class_id": 0, "box_caption": "defective_insulator 0.079", "scores": {"class_score": 0.0791015625}, "domain": "pixel"}, {"position": {"minX": 72.54611206054688, "minY": 36.680938720703125, "maxX": 454.4538879394531, "maxY": 303.5690612792969}, "class_id": 0, "box_caption": "defective_insulator 0.077", "scores": {"class_score": 0.0767822265625}, "domain": "pixel"}, {"position": {"minX": 195.80642700195312, "minY": 8.792388916015625, "maxX": 378.1935729980469, "maxY": 445.2076110839844}, "class_id": 0, "box_caption": "defective_insulator 0.075", "scores": {"class_score": 0.074951171875}, "domain": "pixel"}, {"position": {"minX": 320.1880187988281, "minY": 290.5570068359375, "maxX": 368.3119812011719, "maxY": 367.4429931640625}, "class_id": 3, "box_caption": "flashover_defect 0.073", "scores": {"class_score": 0.073486328125}, "domain": "pixel"}, {"position": {"minX": 400.68316650390625, "minY": -11.397003173828125, "maxX": 602.8168334960938, "maxY": 127.08450317382812}, "class_id": 3, "box_caption": "flashover_defect 0.062", "scores": {"class_score": 0.0616455078125}, "domain": "pixel"}, {"position": {"minX": 221.31988525390625, "minY": 142.31936645507812, "maxX": 302.18011474609375, "maxY": 202.43063354492188}, "class_id": 1, "box_caption": "broken_defect 0.061", "scores": {"class_score": 0.0609130859375}, "domain": "pixel"}, {"position": {"minX": 181.93856811523438, "minY": 57.174461364746094, "maxX": 324.5614318847656, "maxY": 256.5755310058594}, "class_id": 3, "box_caption": "flashover_defect 0.049", "scores": {"class_score": 0.04931640625}, "domain": "pixel"}, {"position": {"minX": 230.43003845214844, "minY": 139.53448486328125, "maxX": 293.5699462890625, "maxY": 217.46551513671875}, "class_id": 1, "box_caption": "broken_defect 0.049", "scores": {"class_score": 0.04925537109375}, "domain": "pixel"}, {"position": {"minX": 218.1217041015625, "minY": 131.44993591308594, "maxX": 285.8782958984375, "maxY": 176.55006408691406}, "class_id": 1, "box_caption": "broken_defect 0.041", "scores": {"class_score": 0.04144287109375}, "domain": "pixel"}, {"position": {"minX": 243.42425537109375, "minY": 165.36065673828125, "maxX": 342.07574462890625, "maxY": 301.38934326171875}, "class_id": 0, "box_caption": "defective_insulator 0.039", "scores": {"class_score": 0.038787841796875}, "domain": "pixel"}, {"position": {"minX": 233.47406005859375, "minY": 145.45144653320312, "maxX": 319.52593994140625, "maxY": 259.2985534667969}, "class_id": 1, "box_caption": "broken_defect 0.038", "scores": {"class_score": 0.038238525390625}, "domain": "pixel"}, {"position": {"minX": 233.47406005859375, "minY": 145.45144653320312, "maxX": 319.52593994140625, "maxY": 259.2985534667969}, "class_id": 0, "box_caption": "defective_insulator 0.035", "scores": {"class_score": 0.035125732421875}, "domain": "pixel"}, {"position": {"minX": 232.188232421875, "minY": 191.584716796875, "maxX": 346.811767578125, "maxY": 265.915283203125}, "class_id": 1, "box_caption": "broken_defect 0.035", "scores": {"class_score": 0.034942626953125}, "domain": "pixel"}, {"position": {"minX": 243.42425537109375, "minY": 165.36065673828125, "maxX": 342.07574462890625, "maxY": 301.38934326171875}, "class_id": 1, "box_caption": "broken_defect 0.032", "scores": {"class_score": 0.03192138671875}, "domain": "pixel"}, {"position": {"minX": 219.44886779785156, "minY": 161.8557586669922, "maxX": 327.5511474609375, "maxY": 232.1442413330078}, "class_id": 1, "box_caption": "broken_defect 0.031", "scores": {"class_score": 0.030670166015625}, "domain": "pixel"}, {"position": {"minX": 131.34619140625, "minY": -35.77117919921875, "maxX": 388.65380859375, "maxY": 350.2711486816406}, "class_id": 0, "box_caption": "defective_insulator 0.030", "scores": {"class_score": 0.03009033203125}, "domain": "pixel"}, {"position": {"minX": 232.188232421875, "minY": 191.584716796875, "maxX": 346.811767578125, "maxY": 265.915283203125}, "class_id": 0, "box_caption": "defective_insulator 0.030", "scores": {"class_score": 0.029937744140625}, "domain": "pixel"}, {"position": {"minX": 205.37213134765625, "minY": 71.90463256835938, "maxX": 386.12786865234375, "maxY": 386.3453674316406}, "class_id": 3, "box_caption": "flashover_defect 0.029", "scores": {"class_score": 0.029022216796875}, "domain": "pixel"}, {"position": {"minX": 244.0057373046875, "minY": 218.73965454101562, "maxX": 370.4942626953125, "maxY": 310.2603454589844}, "class_id": 1, "box_caption": "broken_defect 0.029", "scores": {"class_score": 0.0289306640625}, "domain": "pixel"}, {"position": {"minX": 276.0707092285156, "minY": 226.26034545898438, "maxX": 366.4292907714844, "maxY": 350.7396545410156}, "class_id": 3, "box_caption": "flashover_defect 0.029", "scores": {"class_score": 0.028564453125}, "domain": "pixel"}, {"position": {"minX": 286.21551513671875, "minY": 279.3189392089844, "maxX": 407.78448486328125, "maxY": 370.1810607910156}, "class_id": 1, "box_caption": "broken_defect 0.027", "scores": {"class_score": 0.0265960693359375}, "domain": "pixel"}, {"position": {"minX": 88.42518615722656, "minY": 150.05828857421875, "maxX": 524.5748291015625, "maxY": 319.94171142578125}, "class_id": 0, "box_caption": "defective_insulator 0.025", "scores": {"class_score": 0.024810791015625}, "domain": "pixel"}, {"position": {"minX": 219.44886779785156, "minY": 161.8557586669922, "maxX": 327.5511474609375, "maxY": 232.1442413330078}, "class_id": 0, "box_caption": "defective_insulator 0.024", "scores": {"class_score": 0.0242462158203125}, "domain": "pixel"}, {"position": {"minX": 244.0057373046875, "minY": 218.73965454101562, "maxX": 370.4942626953125, "maxY": 310.2603454589844}, "class_id": 0, "box_caption": "defective_insulator 0.024", "scores": {"class_score": 0.0240478515625}, "domain": "pixel"}, {"position": {"minX": 220.35678100585938, "minY": 144.9993133544922, "maxX": 298.6432189941406, "maxY": 197.7506866455078}, "class_id": 0, "box_caption": "defective_insulator 0.024", "scores": {"class_score": 0.0237274169921875}, "domain": "pixel"}, {"position": {"minX": 1.8955078125, "minY": 269.7579040527344, "maxX": 141.1044921875, "maxY": 369.7420959472656}, "class_id": 3, "box_caption": "flashover_defect 0.024", "scores": {"class_score": 0.023529052734375}, "domain": "pixel"}, {"position": {"minX": 73.04507446289062, "minY": 68.04364013671875, "maxX": 420.7049255371094, "maxY": 210.45635986328125}, "class_id": 0, "box_caption": "defective_insulator 0.022", "scores": {"class_score": 0.02197265625}, "domain": "pixel"}, {"position": {"minX": 161.84423828125, "minY": 49.95942687988281, "maxX": 292.15576171875, "maxY": 157.1655731201172}, "class_id": 3, "box_caption": "flashover_defect 0.022", "scores": {"class_score": 0.021575927734375}, "domain": "pixel"}, {"position": {"minX": 202.11126708984375, "minY": 100.11164855957031, "maxX": 267.38873291015625, "maxY": 142.7633514404297}, "class_id": 1, "box_caption": "broken_defect 0.021", "scores": {"class_score": 0.02117919921875}, "domain": "pixel"}, {"position": {"minX": 76.76290893554688, "minY": 66.59136962890625, "maxX": 468.7370910644531, "maxY": 353.90863037109375}, "class_id": 0, "box_caption": "defective_insulator 0.021", "scores": {"class_score": 0.0210418701171875}, "domain": "pixel"}, {"position": {"minX": 320.1880187988281, "minY": 290.5570068359375, "maxX": 368.3119812011719, "maxY": 367.4429931640625}, "class_id": 1, "box_caption": "broken_defect 0.021", "scores": {"class_score": 0.0208740234375}, "domain": "pixel"}, {"position": {"minX": 164.10601806640625, "minY": 68.35061645507812, "maxX": 307.64398193359375, "maxY": 179.27438354492188}, "class_id": 1, "box_caption": "broken_defect 0.020", "scores": {"class_score": 0.0199432373046875}, "domain": "pixel"}, {"position": {"minX": 70.68814086914062, "minY": 118.54141998291016, "maxX": 511.3118591308594, "maxY": 287.2085876464844}, "class_id": 0, "box_caption": "defective_insulator 0.020", "scores": {"class_score": 0.0198974609375}, "domain": "pixel"}, {"position": {"minX": 261.96600341796875, "minY": 194.18630981445312, "maxX": 325.03399658203125, "maxY": 277.3136901855469}, "class_id": 1, "box_caption": "broken_defect 0.020", "scores": {"class_score": 0.0198974609375}, "domain": "pixel"}, {"position": {"minX": 131.68600463867188, "minY": 6.3001708984375, "maxX": 415.8139953613281, "maxY": 414.4498291015625}, "class_id": 0, "box_caption": "defective_insulator 0.020", "scores": {"class_score": 0.0196533203125}, "domain": "pixel"}, {"position": {"minX": 239.45364379882812, "minY": 158.32659912109375, "maxX": 385.0463562011719, "maxY": 369.67340087890625}, "class_id": 1, "box_caption": "broken_defect 0.019", "scores": {"class_score": 0.018829345703125}, "domain": "pixel"}, {"position": {"minX": 83.56661987304688, "minY": 63.5986328125, "maxX": 430.9333801269531, "maxY": 254.6513671875}, "class_id": 0, "box_caption": "defective_insulator 0.018", "scores": {"class_score": 0.0181884765625}, "domain": "pixel"}, {"position": {"minX": 36.995521545410156, "minY": 277.6941833496094, "maxX": 97.37947845458984, "maxY": 373.3058166503906}, "class_id": 3, "box_caption": "flashover_defect 0.018", "scores": {"class_score": 0.0180816650390625}, "domain": "pixel"}, {"position": {"minX": 271.12286376953125, "minY": 226.57369995117188, "maxX": 349.37713623046875, "maxY": 308.9263000488281}, "class_id": 1, "box_caption": "broken_defect 0.017", "scores": {"class_score": 0.016876220703125}, "domain": "pixel"}, {"position": {"minX": 90.21026611328125, "minY": 42.023345947265625, "maxX": 468.28973388671875, "maxY": 359.7266845703125}, "class_id": 1, "box_caption": "broken_defect 0.017", "scores": {"class_score": 0.0166473388671875}, "domain": "pixel"}, {"position": {"minX": 239.46246337890625, "minY": 170.5236053466797, "maxX": 317.53753662109375, "maxY": 250.9763946533203}, "class_id": 1, "box_caption": "broken_defect 0.015", "scores": {"class_score": 0.01523590087890625}, "domain": "pixel"}, {"position": {"minX": 83.56661987304688, "minY": 63.5986328125, "maxX": 430.9333801269531, "maxY": 254.6513671875}, "class_id": 1, "box_caption": "broken_defect 0.015", "scores": {"class_score": 0.014984130859375}, "domain": "pixel"}, {"position": {"minX": 283.2952575683594, "minY": 273.9674377441406, "maxX": 365.2047424316406, "maxY": 321.0325622558594}, "class_id": 1, "box_caption": "broken_defect 0.014", "scores": {"class_score": 0.01392364501953125}, "domain": "pixel"}, {"position": {"minX": 220.35678100585938, "minY": 144.9993133544922, "maxX": 298.6432189941406, "maxY": 197.7506866455078}, "class_id": 3, "box_caption": "flashover_defect 0.014", "scores": {"class_score": 0.01367950439453125}, "domain": "pixel"}, {"position": {"minX": 180.42514038085938, "minY": 8.4239501953125, "maxX": 401.5748596191406, "maxY": 430.8260498046875}, "class_id": 1, "box_caption": "broken_defect 0.014", "scores": {"class_score": 0.01352691650390625}, "domain": "pixel"}, {"position": {"minX": 400.68316650390625, "minY": -11.397003173828125, "maxX": 602.8168334960938, "maxY": 127.08450317382812}, "class_id": 1, "box_caption": "broken_defect 0.014", "scores": {"class_score": 0.01351165771484375}, "domain": "pixel"}, {"position": {"minX": 320.66766357421875, "minY": 312.30706787109375, "maxX": 390.33233642578125, "maxY": 352.19293212890625}, "class_id": 3, "box_caption": "flashover_defect 0.013", "scores": {"class_score": 0.0128173828125}, "domain": "pixel"}, {"position": {"minX": 211.7808837890625, "minY": 119.65167236328125, "maxX": 290.4691162109375, "maxY": 178.59832763671875}, "class_id": 3, "box_caption": "flashover_defect 0.013", "scores": {"class_score": 0.01276397705078125}, "domain": "pixel"}, {"position": {"minX": 218.1217041015625, "minY": 131.44993591308594, "maxX": 285.8782958984375, "maxY": 176.55006408691406}, "class_id": 0, "box_caption": "defective_insulator 0.012", "scores": {"class_score": 0.0120086669921875}, "domain": "pixel"}, {"position": {"minX": 189.62579345703125, "minY": 70.34223937988281, "maxX": 249.87420654296875, "maxY": 109.40776062011719}, "class_id": 1, "box_caption": "broken_defect 0.011", "scores": {"class_score": 0.0114288330078125}, "domain": "pixel"}, {"position": {"minX": 283.2952575683594, "minY": 273.9674377441406, "maxX": 365.2047424316406, "maxY": 321.0325622558594}, "class_id": 3, "box_caption": "flashover_defect 0.011", "scores": {"class_score": 0.0108184814453125}, "domain": "pixel"}, {"position": {"minX": 427.78546142578125, "minY": -23.553726196289062, "maxX": 557.714599609375, "maxY": 130.74122619628906}, "class_id": 3, "box_caption": "flashover_defect 0.011", "scores": {"class_score": 0.01070404052734375}, "domain": "pixel"}, {"position": {"minX": 202.11126708984375, "minY": 100.11164855957031, "maxX": 267.38873291015625, "maxY": 142.7633514404297}, "class_id": 3, "box_caption": "flashover_defect 0.010", "scores": {"class_score": 0.01006317138671875}, "domain": "pixel"}], "class_labels": {"0": "defective_insulator", "1": "broken_defect", "2": "good_insulator", "3": "flashover_defect"}}