{"box_data": [{"position": {"minX": 229.93447875976562, "minY": -0.405792236328125, "maxX": 340.0655212402344, "maxY": 393.4057922363281}, "class_id": 0, "box_caption": "defective_insulator 0.436", "scores": {"class_score": 0.43603515625}, "domain": "pixel"}, {"position": {"minX": 244.11569213867188, "minY": 9.61798095703125, "maxX": 311.8843078613281, "maxY": 354.13201904296875}, "class_id": 0, "box_caption": "defective_insulator 0.289", "scores": {"class_score": 0.289306640625}, "domain": "pixel"}, {"position": {"minX": 251.87509155273438, "minY": 136.6925048828125, "maxX": 303.1249084472656, "maxY": 259.5574951171875}, "class_id": 0, "box_caption": "defective_insulator 0.128", "scores": {"class_score": 0.1279296875}, "domain": "pixel"}, {"position": {"minX": 257.4645690917969, "minY": 30.17630386352539, "maxX": 305.0354309082031, "maxY": 61.94869613647461}, "class_id": 3, "box_caption": "flashover_defect 0.108", "scores": {"class_score": 0.1077880859375}, "domain": "pixel"}, {"position": {"minX": 251.87509155273438, "minY": 136.6925048828125, "maxX": 303.1249084472656, "maxY": 259.5574951171875}, "class_id": 1, "box_caption": "broken_defect 0.107", "scores": {"class_score": 0.10662841796875}, "domain": "pixel"}, {"position": {"minX": 258.1698913574219, "minY": 192.6519775390625, "maxX": 293.3301086425781, "maxY": 226.0980224609375}, "class_id": 1, "box_caption": "broken_defect 0.106", "scores": {"class_score": 0.10589599609375}, "domain": "pixel"}, {"position": {"minX": 145.94808959960938, "minY": 171.9373779296875, "maxX": 410.0519104003906, "maxY": 217.3126220703125}, "class_id": 0, "box_caption": "defective_insulator 0.092", "scores": {"class_score": 0.09222412109375}, "domain": "pixel"}, {"position": {"minX": 256.6261291503906, "minY": 206.8997344970703, "maxX": 297.3738708496094, "maxY": 231.1002655029297}, "class_id": 1, "box_caption": "broken_defect 0.087", "scores": {"class_score": 0.0870361328125}, "domain": "pixel"}, {"position": {"minX": 253.77920532226562, "minY": 178.31126403808594, "maxX": 298.7207946777344, "maxY": 211.93873596191406}, "class_id": 1, "box_caption": "broken_defect 0.072", "scores": {"class_score": 0.071533203125}, "domain": "pixel"}, {"position": {"minX": 256.08233642578125, "minY": 216.40541076660156, "maxX": 297.91766357421875, "maxY": 242.09458923339844}, "class_id": 1, "box_caption": "broken_defect 0.069", "scores": {"class_score": 0.06866455078125}, "domain": "pixel"}, {"position": {"minX": 233.74392700195312, "minY": 65.6817626953125, "maxX": 323.7560729980469, "maxY": 304.3182373046875}, "class_id": 1, "box_caption": "broken_defect 0.069", "scores": {"class_score": 0.06854248046875}, "domain": "pixel"}, {"position": {"minX": 229.81201171875, "minY": 197.60914611816406, "maxX": 325.18798828125, "maxY": 227.64085388183594}, "class_id": 1, "box_caption": "broken_defect 0.067", "scores": {"class_score": 0.0665283203125}, "domain": "pixel"}, {"position": {"minX": 229.81201171875, "minY": 197.60914611816406, "maxX": 325.18798828125, "maxY": 227.64085388183594}, "class_id": 0, "box_caption": "defective_insulator 0.062", "scores": {"class_score": 0.061920166015625}, "domain": "pixel"}, {"position": {"minX": 121.93109130859375, "minY": 144.17002868652344, "maxX": 434.56890869140625, "maxY": 199.82997131347656}, "class_id": 0, "box_caption": "defective_insulator 0.061", "scores": {"class_score": 0.060516357421875}, "domain": "pixel"}, {"position": {"minX": 260.22320556640625, "minY": 131.6827392578125, "maxX": 300.77679443359375, "maxY": 180.3172607421875}, "class_id": 1, "box_caption": "broken_defect 0.054", "scores": {"class_score": 0.054473876953125}, "domain": "pixel"}, {"position": {"minX": 249.40231323242188, "minY": 310.3076477050781, "maxX": 291.0976867675781, "maxY": 342.1923522949219}, "class_id": 3, "box_caption": "flashover_defect 0.053", "scores": {"class_score": 0.0528564453125}, "domain": "pixel"}, {"position": {"minX": 256.4179382324219, "minY": 227.8134765625, "maxX": 298.5820617675781, "maxY": 257.9365234375}, "class_id": 1, "box_caption": "broken_defect 0.050", "scores": {"class_score": 0.05047607421875}, "domain": "pixel"}, {"position": {"minX": 261.8434753417969, "minY": 38.194461822509766, "maxX": 300.1565246582031, "maxY": 62.493038177490234}, "class_id": 1, "box_caption": "broken_defect 0.047", "scores": {"class_score": 0.04681396484375}, "domain": "pixel"}, {"position": {"minX": 163.65463256835938, "minY": 30.030120849609375, "maxX": 401.3453674316406, "maxY": 294.9698791503906}, "class_id": 0, "box_caption": "defective_insulator 0.047", "scores": {"class_score": 0.0465087890625}, "domain": "pixel"}, {"position": {"minX": 164.8311309814453, "minY": 72.76177978515625, "maxX": 397.66888427734375, "maxY": 332.23822021484375}, "class_id": 0, "box_caption": "defective_insulator 0.045", "scores": {"class_score": 0.044830322265625}, "domain": "pixel"}, {"position": {"minX": 255.42100524902344, "minY": 244.21014404296875, "maxX": 298.0789794921875, "maxY": 273.28985595703125}, "class_id": 1, "box_caption": "broken_defect 0.042", "scores": {"class_score": 0.04248046875}, "domain": "pixel"}, {"position": {"minX": 145.94808959960938, "minY": 171.9373779296875, "maxX": 410.0519104003906, "maxY": 217.3126220703125}, "class_id": 1, "box_caption": "broken_defect 0.041", "scores": {"class_score": 0.040679931640625}, "domain": "pixel"}, {"position": {"minX": 257.1982421875, "minY": 161.08917236328125, "maxX": 296.8017578125, "maxY": 184.16082763671875}, "class_id": 1, "box_caption": "broken_defect 0.040", "scores": {"class_score": 0.03955078125}, "domain": "pixel"}, {"position": {"minX": 225.2803955078125, "minY": 140.59860229492188, "maxX": 330.2196044921875, "maxY": 171.15139770507812}, "class_id": 0, "box_caption": "defective_insulator 0.037", "scores": {"class_score": 0.03729248046875}, "domain": "pixel"}, {"position": {"minX": 257.3363952636719, "minY": 117.41688537597656, "maxX": 299.6636047363281, "maxY": 143.58311462402344}, "class_id": 1, "box_caption": "broken_defect 0.036", "scores": {"class_score": 0.036346435546875}, "domain": "pixel"}, {"position": {"minX": 259.3145446777344, "minY": 129.4829559326172, "maxX": 297.6854553222656, "maxY": 153.5170440673828}, "class_id": 1, "box_caption": "broken_defect 0.036", "scores": {"class_score": 0.03558349609375}, "domain": "pixel"}, {"position": {"minX": 257.31103515625, "minY": 192.02549743652344, "maxX": 296.18896484375, "maxY": 216.47450256347656}, "class_id": 0, "box_caption": "defective_insulator 0.035", "scores": {"class_score": 0.035308837890625}, "domain": "pixel"}, {"position": {"minX": 225.2803955078125, "minY": 140.59860229492188, "maxX": 330.2196044921875, "maxY": 171.15139770507812}, "class_id": 1, "box_caption": "broken_defect 0.035", "scores": {"class_score": 0.03515625}, "domain": "pixel"}, {"position": {"minX": 260.22320556640625, "minY": 131.6827392578125, "maxX": 300.77679443359375, "maxY": 180.3172607421875}, "class_id": 0, "box_caption": "defective_insulator 0.035", "scores": {"class_score": 0.03509521484375}, "domain": "pixel"}, {"position": {"minX": 250.62460327148438, "minY": 102.927490234375, "maxX": 312.3753967285156, "maxY": 208.322509765625}, "class_id": 1, "box_caption": "broken_defect 0.033", "scores": {"class_score": 0.0330810546875}, "domain": "pixel"}, {"position": {"minX": 258.1698913574219, "minY": 192.6519775390625, "maxX": 293.3301086425781, "maxY": 226.0980224609375}, "class_id": 3, "box_caption": "flashover_defect 0.031", "scores": {"class_score": 0.0311431884765625}, "domain": "pixel"}, {"position": {"minX": 250.62460327148438, "minY": 102.927490234375, "maxX": 312.3753967285156, "maxY": 208.322509765625}, "class_id": 0, "box_caption": "defective_insulator 0.030", "scores": {"class_score": 0.0301666259765625}, "domain": "pixel"}, {"position": {"minX": 245.63839721679688, "minY": 324.0436096191406, "maxX": 287.8616027832031, "maxY": 350.4563903808594}, "class_id": 3, "box_caption": "flashover_defect 0.030", "scores": {"class_score": 0.030029296875}, "domain": "pixel"}, {"position": {"minX": 255.2718048095703, "minY": 176.88418579101562, "maxX": 298.72821044921875, "maxY": 202.36581420898438}, "class_id": 0, "box_caption": "defective_insulator 0.030", "scores": {"class_score": 0.029998779296875}, "domain": "pixel"}, {"position": {"minX": 253.2493896484375, "minY": 264.4432067871094, "maxX": 292.7506103515625, "maxY": 291.5567932128906}, "class_id": 1, "box_caption": "broken_defect 0.030", "scores": {"class_score": 0.0299072265625}, "domain": "pixel"}, {"position": {"minX": 251.79583740234375, "minY": 297.90997314453125, "maxX": 290.70416259765625, "maxY": 328.59002685546875}, "class_id": 3, "box_caption": "flashover_defect 0.029", "scores": {"class_score": 0.028778076171875}, "domain": "pixel"}, {"position": {"minX": 257.2780456542969, "minY": 207.97198486328125, "maxX": 296.2219543457031, "maxY": 238.77801513671875}, "class_id": 3, "box_caption": "flashover_defect 0.029", "scores": {"class_score": 0.028564453125}, "domain": "pixel"}, {"position": {"minX": 253.72198486328125, "minY": 279.657470703125, "maxX": 291.27801513671875, "maxY": 307.342529296875}, "class_id": 3, "box_caption": "flashover_defect 0.028", "scores": {"class_score": 0.0279541015625}, "domain": "pixel"}, {"position": {"minX": 256.4179382324219, "minY": 227.8134765625, "maxX": 298.5820617675781, "maxY": 257.9365234375}, "class_id": 3, "box_caption": "flashover_defect 0.027", "scores": {"class_score": 0.02728271484375}, "domain": "pixel"}, {"position": {"minX": 255.42100524902344, "minY": 244.21014404296875, "maxX": 298.0789794921875, "maxY": 273.28985595703125}, "class_id": 3, "box_caption": "flashover_defect 0.026", "scores": {"class_score": 0.0261383056640625}, "domain": "pixel"}, {"position": {"minX": 260.22320556640625, "minY": 131.6827392578125, "maxX": 300.77679443359375, "maxY": 180.3172607421875}, "class_id": 3, "box_caption": "flashover_defect 0.025", "scores": {"class_score": 0.0247955322265625}, "domain": "pixel"}, {"position": {"minX": 237.5789794921875, "minY": 118.91160583496094, "maxX": 323.9210205078125, "maxY": 176.08839416503906}, "class_id": 1, "box_caption": "broken_defect 0.024", "scores": {"class_score": 0.024383544921875}, "domain": "pixel"}, {"position": {"minX": 251.87509155273438, "minY": 136.6925048828125, "maxX": 303.1249084472656, "maxY": 259.5574951171875}, "class_id": 3, "box_caption": "flashover_defect 0.023", "scores": {"class_score": 0.022979736328125}, "domain": "pixel"}, {"position": {"minX": 255.56088256835938, "minY": 261.1944274902344, "maxX": 295.9391174316406, "maxY": 289.3055725097656}, "class_id": 3, "box_caption": "flashover_defect 0.023", "scores": {"class_score": 0.0227813720703125}, "domain": "pixel"}, {"position": {"minX": 254.96038818359375, "minY": 217.00022888183594, "maxX": 299.53961181640625, "maxY": 241.24977111816406}, "class_id": 0, "box_caption": "defective_insulator 0.023", "scores": {"class_score": 0.0227508544921875}, "domain": "pixel"}, {"position": {"minX": 261.1673583984375, "minY": 42.810508728027344, "maxX": 300.8326416015625, "maxY": 70.75199127197266}, "class_id": 3, "box_caption": "flashover_defect 0.022", "scores": {"class_score": 0.0221710205078125}, "domain": "pixel"}, {"position": {"minX": 237.5789794921875, "minY": 118.91160583496094, "maxX": 323.9210205078125, "maxY": 176.08839416503906}, "class_id": 0, "box_caption": "defective_insulator 0.022", "scores": {"class_score": 0.021728515625}, "domain": "pixel"}, {"position": {"minX": 121.93109130859375, "minY": 144.17002868652344, "maxX": 434.56890869140625, "maxY": 199.82997131347656}, "class_id": 1, "box_caption": "broken_defect 0.021", "scores": {"class_score": 0.0214080810546875}, "domain": "pixel"}, {"position": {"minX": 256.545166015625, "minY": 160.23434448242188, "maxX": 297.454833984375, "maxY": 184.76565551757812}, "class_id": 0, "box_caption": "defective_insulator 0.021", "scores": {"class_score": 0.0205078125}, "domain": "pixel"}, {"position": {"minX": 253.72198486328125, "minY": 279.657470703125, "maxX": 291.27801513671875, "maxY": 307.342529296875}, "class_id": 1, "box_caption": "broken_defect 0.018", "scores": {"class_score": 0.0180511474609375}, "domain": "pixel"}, {"position": {"minX": 258.7135925292969, "minY": 120.84283447265625, "maxX": 299.7864074707031, "maxY": 153.65716552734375}, "class_id": 3, "box_caption": "flashover_defect 0.017", "scores": {"class_score": 0.0165557861328125}, "domain": "pixel"}, {"position": {"minX": 259.6092834472656, "minY": 88.10809326171875, "maxX": 301.8907165527344, "maxY": 118.01690673828125}, "class_id": 1, "box_caption": "broken_defect 0.016", "scores": {"class_score": 0.016082763671875}, "domain": "pixel"}, {"position": {"minX": 241.32940673828125, "minY": 31.840728759765625, "maxX": 330.67059326171875, "maxY": 354.65924072265625}, "class_id": 3, "box_caption": "flashover_defect 0.016", "scores": {"class_score": 0.0159912109375}, "domain": "pixel"}, {"position": {"minX": 246.5858154296875, "minY": 195.1614532470703, "maxX": 312.9141845703125, "maxY": 242.0885467529297}, "class_id": 0, "box_caption": "defective_insulator 0.016", "scores": {"class_score": 0.01568603515625}, "domain": "pixel"}, {"position": {"minX": 261.6919250488281, "minY": 71.87554931640625, "maxX": 303.8080749511719, "maxY": 100.62445068359375}, "class_id": 1, "box_caption": "broken_defect 0.016", "scores": {"class_score": 0.01560211181640625}, "domain": "pixel"}, {"position": {"minX": 181.93157958984375, "minY": 84.84884643554688, "maxX": 380.56842041015625, "maxY": 305.65118408203125}, "class_id": 1, "box_caption": "broken_defect 0.016", "scores": {"class_score": 0.01555633544921875}, "domain": "pixel"}, {"position": {"minX": 260.6922912597656, "minY": 38.565948486328125, "maxX": 302.8077087402344, "maxY": 61.934051513671875}, "class_id": 0, "box_caption": "defective_insulator 0.014", "scores": {"class_score": 0.014251708984375}, "domain": "pixel"}, {"position": {"minX": 254.97958374023438, "minY": 129.57701110839844, "maxX": 300.5204162597656, "maxY": 153.67298889160156}, "class_id": 0, "box_caption": "defective_insulator 0.014", "scores": {"class_score": 0.01422119140625}, "domain": "pixel"}, {"position": {"minX": 258.029052734375, "minY": 103.91670227050781, "maxX": 300.470947265625, "maxY": 130.3332977294922}, "class_id": 1, "box_caption": "broken_defect 0.014", "scores": {"class_score": 0.01412200927734375}, "domain": "pixel"}, {"position": {"minX": 244.11569213867188, "minY": 9.61798095703125, "maxX": 311.8843078613281, "maxY": 354.13201904296875}, "class_id": 2, "box_caption": "good_insulator 0.014", "scores": {"class_score": 0.0139617919921875}, "domain": "pixel"}, {"position": {"minX": 258.34912109375, "minY": 104.45965576171875, "maxX": 301.65087890625, "maxY": 136.79034423828125}, "class_id": 3, "box_caption": "flashover_defect 0.014", "scores": {"class_score": 0.01374053955078125}, "domain": "pixel"}, {"position": {"minX": 163.65463256835938, "minY": 30.030120849609375, "maxX": 401.3453674316406, "maxY": 294.9698791503906}, "class_id": 1, "box_caption": "broken_defect 0.014", "scores": {"class_score": 0.01369476318359375}, "domain": "pixel"}, {"position": {"minX": 258.8096618652344, "minY": 48.15959167480469, "maxX": 304.6903381347656, "maxY": 81.96540832519531}, "class_id": 1, "box_caption": "broken_defect 0.013", "scores": {"class_score": 0.01329803466796875}, "domain": "pixel"}, {"position": {"minX": 220.01019287109375, "minY": -25.26458740234375, "maxX": 345.48980712890625, "maxY": 388.76458740234375}, "class_id": 2, "box_caption": "good_insulator 0.013", "scores": {"class_score": 0.01322174072265625}, "domain": "pixel"}, {"position": {"minX": 261.6919250488281, "minY": 71.87554931640625, "maxX": 303.8080749511719, "maxY": 100.62445068359375}, "class_id": 3, "box_caption": "flashover_defect 0.013", "scores": {"class_score": 0.01255035400390625}, "domain": "pixel"}, {"position": {"minX": 242.53082275390625, "minY": 309.53338623046875, "maxX": 292.46917724609375, "maxY": 353.46661376953125}, "class_id": 1, "box_caption": "broken_defect 0.012", "scores": {"class_score": 0.0124053955078125}, "domain": "pixel"}, {"position": {"minX": 259.6092834472656, "minY": 88.10809326171875, "maxX": 301.8907165527344, "maxY": 118.01690673828125}, "class_id": 3, "box_caption": "flashover_defect 0.012", "scores": {"class_score": 0.01239776611328125}, "domain": "pixel"}, {"position": {"minX": 182.9803466796875, "minY": 43.152923583984375, "maxX": 346.5196533203125, "maxY": 361.09710693359375}, "class_id": 0, "box_caption": "defective_insulator 0.011", "scores": {"class_score": 0.01136016845703125}, "domain": "pixel"}, {"position": {"minX": 253.77920532226562, "minY": 178.31126403808594, "maxX": 298.7207946777344, "maxY": 211.93873596191406}, "class_id": 3, "box_caption": "flashover_defect 0.011", "scores": {"class_score": 0.0113525390625}, "domain": "pixel"}, {"position": {"minX": 8.28436279296875, "minY": 10.698165893554688, "maxX": 101.59063720703125, "maxY": 105.48933410644531}, "class_id": 3, "box_caption": "flashover_defect 0.011", "scores": {"class_score": 0.01134490966796875}, "domain": "pixel"}, {"position": {"minX": 254.32757568359375, "minY": 118.51315307617188, "maxX": 302.17242431640625, "maxY": 142.48684692382812}, "class_id": 0, "box_caption": "defective_insulator 0.010", "scores": {"class_score": 0.0102996826171875}, "domain": "pixel"}], "class_labels": {"0": "defective_insulator", "1": "broken_defect", "2": "good_insulator", "3": "flashover_defect"}}