<annotation verified="no">
  <folder>JPEGImages</folder>
  <filename>000020</filename>
  <path>F:\A-zk\Rotating target\JPEGImages\000020.jpg</path>
  <source>
    <database>Unknown</database>
  </source>
  <size>
    <width>1286</width>
    <height>854</height>
    <depth>3</depth>
  </size>
  <segmented>0</segmented>
  <object>
    <type>robndbox</type>
    <name>defective_insulator</name>
    <pose>Unspecified</pose>
    <truncated>0</truncated>
    <difficult>0</difficult>
    <robndbox>
      <cx>646.521</cx>
      <cy>426.5168</cy>
      <w>450.0</w>
      <h>853.0</h>
      <angle>0.0</angle>
    </robndbox>
  </object>
  <object>
    <type>robndbox</type>
    <name>broken_defect</name>
    <pose>Unspecified</pose>
    <truncated>0</truncated>
    <difficult>0</difficult>
    <robndbox>
      <cx>657.7497</cx>
      <cy>431.7236</cy>
      <w>352.5185</w>
      <h>217.2895</h>
      <angle>0.07</angle>
    </robndbox>
  </object>
  <object>
    <type>robndbox</type>
    <name>broken_defect</name>
    <pose>Unspecified</pose>
    <truncated>0</truncated>
    <difficult>0</difficult>
    <robndbox>
      <cx>633.3887</cx>
      <cy>588.4829</cy>
      <w>340.5527</w>
      <h>212.4003</h>
      <angle>0.09</angle>
    </robndbox>
  </object>
</annotation>
