<annotation verified="no">
  <folder>JPEGImages</folder>
  <filename>000539</filename>
  <path>F:\A-zk\Rotating target\JPEGImages\000539.jpg</path>
  <source>
    <database>Unknown</database>
  </source>
  <size>
    <width>2208</width>
    <height>1472</height>
    <depth>3</depth>
  </size>
  <segmented>0</segmented>
  <object>
    <type>robndbox</type>
    <name>defective_insulator</name>
    <pose>Unspecified</pose>
    <truncated>0</truncated>
    <difficult>0</difficult>
    <robndbox>
      <cx>1062.4574</cx>
      <cy>986.9311</cy>
      <w>188.7956</w>
      <h>914.1124</h>
      <angle>0.22</angle>
    </robndbox>
  </object>
  <object>
    <type>robndbox</type>
    <name>flashover_defect</name>
    <pose>Unspecified</pose>
    <truncated>0</truncated>
    <difficult>0</difficult>
    <robndbox>
      <cx>1143.6709</cx>
      <cy>618.7204</cy>
      <w>182.6879</w>
      <h>155.584</h>
      <angle>0.22</angle>
    </robndbox>
  </object>
</annotation>
