<annotation verified="no">
  <folder>JPEGImages</folder>
  <filename>000762</filename>
  <path>F:\A-zk\Rotating target\JPEGImages\000762.jpg</path>
  <source>
    <database>Unknown</database>
  </source>
  <size>
    <width>1152</width>
    <height>864</height>
    <depth>3</depth>
  </size>
  <segmented>0</segmented>
  <object>
    <type>robndbox</type>
    <name>good_insulator</name>
    <pose>Unspecified</pose>
    <truncated>0</truncated>
    <difficult>0</difficult>
    <robndbox>
      <cx>533.2406</cx>
      <cy>462.3408</cy>
      <w>779.3463</w>
      <h>76.6348</h>
      <angle>3.031593</angle>
    </robndbox>
  </object>
</annotation>
