<annotation verified="no">
  <folder>JPEGImages</folder>
  <filename>000095</filename>
  <path>F:\A-zk\Rotating target\JPEGImages\000095.jpg</path>
  <source>
    <database>Unknown</database>
  </source>
  <size>
    <width>2400</width>
    <height>1600</height>
    <depth>3</depth>
  </size>
  <segmented>0</segmented>
  <object>
    <type>robndbox</type>
    <name>defective_insulator</name>
    <pose>Unspecified</pose>
    <truncated>0</truncated>
    <difficult>0</difficult>
    <bndbox>
      <x0>338</x0><y0>563</y0><x1>1844</x1><y1>714</y1><x2>1815</x2><y2>1005</y2><x3>309</x3><y3>854</y3></bndbox>
  </object>
  <object>
    <type>robndbox</type>
    <name>flashover_defect</name>
    <pose>Unspecified</pose>
    <truncated>0</truncated>
    <difficult>0</difficult>
    <bndbox>
      <x0>1697</x0><y0>730</y0><x1>1831</x1><y1>743</y1><x2>1806</x2><y2>991</y2><x3>1672</x3><y3>978</y3></bndbox>
  </object>
  <object>
    <type>robndbox</type>
    <name>flashover_defect</name>
    <pose>Unspecified</pose>
    <truncated>0</truncated>
    <difficult>0</difficult>
    <bndbox>
      <x0>1630</x0><y0>715</y0><x1>1758</x1><y1>728</y1><x2>1732</x2><y2>984</y2><x3>1604</x3><y3>971</y3></bndbox>
  </object>
  <object>
    <type>robndbox</type>
    <name>flashover_defect</name>
    <pose>Unspecified</pose>
    <truncated>0</truncated>
    <difficult>0</difficult>
    <bndbox>
      <x0>1130</x0><y0>662</y0><x1>1273</x1><y1>678</y1><x2>1243</x2><y2>945</y2><x3>1100</x3><y3>930</y3></bndbox>
  </object>
  <object>
    <type>robndbox</type>
    <name>flashover_defect</name>
    <pose>Unspecified</pose>
    <truncated>0</truncated>
    <difficult>0</difficult>
    <bndbox>
      <x0>1398</x0><y0>692</y0><x1>1524</x1><y1>708</y1><x2>1490</x2><y2>968</y2><x3>1364</x3><y3>951</y3></bndbox>
  </object>
  <object>
    <type>robndbox</type>
    <name>flashover_defect</name>
    <pose>Unspecified</pose>
    <truncated>0</truncated>
    <difficult>0</difficult>
    <bndbox>
      <x0>352</x0><y0>562</y0><x1>567</x1><y1>586</y1><x2>537</x2><y2>858</y2><x3>322</x3><y3>834</y3></bndbox>
  </object>
  <object>
    <type>robndbox</type>
    <name>good_insulator</name>
    <pose>Unspecified</pose>
    <truncated>0</truncated>
    <difficult>0</difficult>
    <bndbox>
      <x0>1833</x0><y0>0</y0><x1>2384</x1><y1>0</y1><x2>2384</x2><y2>729</y2><x3>1833</x3><y3>729</y3></bndbox>
  </object>
</annotation>