<annotation verified="no">
  <folder>JPEGImages</folder>
  <filename>000249</filename>
  <path>F:\A-zk\Rotating target\JPEGImages\000249.jpg</path>
  <source>
    <database>Unknown</database>
  </source>
  <size>
    <width>1804</width>
    <height>1203</height>
    <depth>3</depth>
  </size>
  <segmented>0</segmented>
  <object>
    <type>robndbox</type>
    <name>defective_insulator</name>
    <pose>Unspecified</pose>
    <truncated>0</truncated>
    <difficult>0</difficult>
    <bndbox>
      <x0>701</x0><y0>453</y0><x1>1032</x1><y1>453</y1><x2>1032</x2><y2>1202</y2><x3>701</x3><y3>1202</y3></bndbox>
  </object>
  <object>
    <type>robndbox</type>
    <name>flashover_defect</name>
    <pose>Unspecified</pose>
    <truncated>0</truncated>
    <difficult>0</difficult>
    <bndbox>
      <x0>709</x0><y0>458</y0><x1>1035</x1><y1>458</y1><x2>1035</x2><y2>685</y2><x3>709</x3><y3>685</y3></bndbox>
  </object>
  <object>
    <type>robndbox</type>
    <name>flashover_defect</name>
    <pose>Unspecified</pose>
    <truncated>0</truncated>
    <difficult>0</difficult>
    <bndbox>
      <x0>712</x0><y0>780</y0><x1>1039</x1><y1>780</y1><x2>1039</x2><y2>972</y2><x3>712</x3><y3>972</y3></bndbox>
  </object>
  <object>
    <type>robndbox</type>
    <name>flashover_defect</name>
    <pose>Unspecified</pose>
    <truncated>0</truncated>
    <difficult>0</difficult>
    <bndbox>
      <x0>709</x0><y0>1082</y0><x1>1031</x1><y1>1082</y1><x2>1031</x2><y2>1201</y2><x3>709</x3><y3>1201</y3></bndbox>
  </object>
</annotation>