<annotation verified="no">
  <folder>JPEGImages</folder>
  <filename>000195</filename>
  <path>F:\A-zk\Rotating target\JPEGImages\000195.jpg</path>
  <source>
    <database>Unknown</database>
  </source>
  <size>
    <width>1804</width>
    <height>1203</height>
    <depth>3</depth>
  </size>
  <segmented>0</segmented>
  <object>
    <type>robndbox</type>
    <name>defective_insulator</name>
    <pose>Unspecified</pose>
    <truncated>0</truncated>
    <difficult>0</difficult>
    <bndbox>
      <x0>797</x0><y0>490</y0><x1>1095</x1><y1>490</y1><x2>1095</x2><y2>1200</y2><x3>797</x3><y3>1200</y3></bndbox>
  </object>
  <object>
    <type>robndbox</type>
    <name>flashover_defect</name>
    <pose>Unspecified</pose>
    <truncated>0</truncated>
    <difficult>0</difficult>
    <bndbox>
      <x0>800</x0><y0>488</y0><x1>1079</x1><y1>488</y1><x2>1079</x2><y2>655</y2><x3>800</x3><y3>655</y3></bndbox>
  </object>
  <object>
    <type>robndbox</type>
    <name>flashover_defect</name>
    <pose>Unspecified</pose>
    <truncated>0</truncated>
    <difficult>0</difficult>
    <bndbox>
      <x0>807</x0><y0>750</y0><x1>1084</x1><y1>750</y1><x2>1084</x2><y2>898</y2><x3>807</x3><y3>898</y3></bndbox>
  </object>
</annotation>