<annotation verified="no">
  <folder>JPEGImages</folder>
  <filename>000574</filename>
  <path>F:\A-zk\Rotating target\JPEGImages\000574.jpg</path>
  <source>
    <database>Unknown</database>
  </source>
  <size>
    <width>1766</width>
    <height>1324</height>
    <depth>3</depth>
  </size>
  <segmented>0</segmented>
  <object>
    <type>robndbox</type>
    <name>defective_insulator</name>
    <pose>Unspecified</pose>
    <truncated>0</truncated>
    <difficult>0</difficult>
    <robndbox>
      <cx>487.1744</cx>
      <cy>810.3759</cy>
      <w>200.8884</w>
      <h>966.8502</h>
      <angle>1.2</angle>
    </robndbox>
  </object>
  <object>
    <type>robndbox</type>
    <name>broken_defect</name>
    <pose>Unspecified</pose>
    <truncated>0</truncated>
    <difficult>0</difficult>
    <robndbox>
      <cx>799.3128</cx>
      <cy>688.518</cy>
      <w>198.2464</w>
      <h>108.9421</h>
      <angle>1.2</angle>
    </robndbox>
  </object>
  <object>
    <type>robndbox</type>
    <name>broken_defect</name>
    <pose>Unspecified</pose>
    <truncated>0</truncated>
    <difficult>0</difficult>
    <robndbox>
      <cx>319.5</cx>
      <cy>881.1667</cy>
      <w>186.1905</w>
      <h>113.9215</h>
      <angle>1.22</angle>
    </robndbox>
  </object>
  <object>
    <type>robndbox</type>
    <name>broken_defect</name>
    <pose>Unspecified</pose>
    <truncated>0</truncated>
    <difficult>0</difficult>
    <robndbox>
      <cx>112.2614</cx>
      <cy>959.1677</cy>
      <w>188.5815</w>
      <h>104.2266</h>
      <angle>1.2</angle>
    </robndbox>
  </object>
</annotation>
